pofium/__init__.py
pofium/pofium.py
pofium-0.1.8.dist-info/LICENSE
pofium-0.1.8.dist-info/METADATA
pofium-0.1.8.dist-info/WHEEL
pofium-0.1.8.dist-info/top_level.txt
pofium-0.1.8.dist-info/RECORD
