Metadata-Version: 2.1
Name: pofium
Version: 0.1.8
Summary: Pacote para download e processamento dos microdados da POF do IBGE.
Home-page: https://github.com/ggximenez/pofium
Author: Gustavo G. Ximenez
Author-email: ggximenez@gmail.com
Classifier: Programming Language :: Python :: 3
Classifier: License :: OSI Approved :: MIT License
Classifier: Operating System :: OS Independent
Requires-Python: >=3.6
License-File: LICENSE
Requires-Dist: pandas
Requires-Dist: numpy
Requires-Dist: unidecode
